fc_wangyishuang.py
fc_wangys-1.0.dist-info/METADATA
fc_wangys-1.0.dist-info/WHEEL
fc_wangys-1.0.dist-info/top_level.txt
fc_wangys-1.0.dist-info/RECORD
