Metadata-Version: 2.1
Name: fc-wangys
Version: 1.0
Summary: 大数据1
Home-page: UNKNOWN
Author: 大数据1
Author-email: fc@wangyishuang.com
License: UNKNOWN
Platform: UNKNOWN
